simplearray/__init__.py
simplearray/array.py
simplearray-0.1.0.dist-info/LICENSE
simplearray-0.1.0.dist-info/METADATA
simplearray-0.1.0.dist-info/WHEEL
simplearray-0.1.0.dist-info/top_level.txt
simplearray-0.1.0.dist-info/RECORD
