Metadata-Version: 2.2
Name: simplearray
Version: 0.1.0
Summary: A simple library that returns a NumPy array
Home-page: https://github.com/yourusername/simplearray
Author: Your Name
Author-email: your@email.com
Classifier: Programming Language :: Python :: 3
Classifier: License :: OSI Approved :: MIT License
Classifier: Operating System :: OS Independent
Requires-Python: >=3.6
License-File: LICENSE
Requires-Dist: numpy
Dynamic: author
Dynamic: author-email
Dynamic: classifier
Dynamic: home-page
Dynamic: requires-dist
Dynamic: requires-python
Dynamic: summary
